soma_songs-1.0.3.dist-info/METADATA
soma_songs-1.0.3.dist-info/WHEEL
soma_songs-1.0.3.dist-info/entry_points.txt
soma_songs-1.0.3.dist-info/licenses/LICENSE
soma_songs/__init__.py
soma_songs/main.py
soma_songs-1.0.3.dist-info/RECORD
