Metadata-Version: 2.1
Name: soma-songs
Version: 1.0.3
Summary: Save song data from somafm.com as JSON
Keywords: music scraper json somafm
Author-Email: inktrap <inktrap@inktrap.org>
License: MIT
Classifier: Development Status :: 5 - Production/Stable
Classifier: Environment :: Console
Classifier: Operating System :: POSIX :: Linux
Classifier: Programming Language :: Python :: 3.8
Classifier: Programming Language :: Python :: 3.9
Classifier: Programming Language :: Python :: 3.10
Classifier: Programming Language :: Python :: 3.11
Project-URL: Homepage, https://github.com/inktrap/soma-songs
Requires-Python: >=3.8
Requires-Dist: beautifulsoup4>=4.12.2
Requires-Dist: tinydb>=4.8.0
Requires-Dist: requests>=2.31.0
Requires-Dist: rich>=13.5.2
Requires-Dist: requests-cache>=1.1.0; extra == "dev"
Requires-Dist: pre-commit; extra == "dev"
Provides-Extra: dev
